Backflows/__init__.py
Backflows/base.py
Backflows/linkSpider.py
Backflows/middleware.py
Backflows/runner.py
Backflows/template.py
Backflows/template_project.py
backflow_core/__init__.py
backflow_core/downloadMiddleware.py
backflow_core/pipeline.py
backflow_core/settings.py
backflow_core/tasks.py
backflow_core/spiders/__init__.py
backflow_core/spiders/dongfangcaifu.py
conf/__init__.py
conf/local.py
conf/pro.py
emojis/__init__.py
emojis/emoji.py
emojis/static.py
example/__init__.py
example/test_spider.py
log/__init__.py
spider_comments/__init__.py
spider_comments/toutiao.py
spiders/__init__.py
spiders/dongfangcaifu.py
test/__init__.py
utils/__init__.py
utils/celery_app.py
utils/ding.py
utils/projectTree.py
utils/restart_celery.py
utils/tools.py
backflow-0.2.4.dist-info/LICENSE
backflow-0.2.4.dist-info/METADATA
backflow-0.2.4.dist-info/WHEEL
backflow-0.2.4.dist-info/entry_points.txt
backflow-0.2.4.dist-info/top_level.txt
backflow-0.2.4.dist-info/RECORD
