Metadata-Version: 2.1
Name: backflow
Version: 0.2.4
Summary: A simple crawler framework that implements both single run and distributed run based on Celery, allowing you to write your crawler code as you please
Home-page: https://github.com/redpintings/Flowback
Author: ysl
Author-email: runfastpluszz@gmail.com
License: MIT
Classifier: Programming Language :: Python :: 3
Classifier: License :: OSI Approved :: MIT License
Classifier: Operating System :: OS Independent
Requires-Python: >=3.6
License-File: LICENSE
Requires-Dist: aiohttp==3.10.11
Requires-Dist: celery==5.2.7
Requires-Dist: elasticsearch==7.17.3
Requires-Dist: loguru
Requires-Dist: PyExecJS
Requires-Dist: requests
Requires-Dist: pymongo
Requires-Dist: argparse
Requires-Dist: tqdm
Requires-Dist: httpx
Requires-Dist: Js2Py
Requires-Dist: watchdog
Requires-Dist: tldextract
Requires-Dist: lxml
Requires-Dist: beautifulsoup4
Requires-Dist: pytz
Requires-Dist: chardet
Requires-Dist: tenacity
Requires-Dist: parsel
Requires-Dist: jmespath
Requires-Dist: redis
